{
  "shape": [
    1,
    14
  ],
  "rows_per_file": 16384,
  "compression": "snappy",
  "timestamp_column": "database_timestamp_ns",
  "schema": [
    {
      "name": "packet_time_ms",
      "type": "float64"
    },
    {
      "name": "pressure_copv_psi",
      "type": "float64"
    },
    {
      "name": "pressure_lox_psi",
      "type": "float64"
    },
    {
      "name": "pressure_lng_psi",
      "type": "float64"
    },
    {
      "name": "pressure_inj_lox_psi",
      "type": "float64"
    },
    {
      "name": "pressure_inj_lng_psi",
      "type": "float64"
    },
    {
      "name": "temperature_copv_c",
      "type": "float64"
    },
    {
      "name": "temperature_c",
      "type": "float64"
    },
    {
      "name": "packet_rssi",
      "type": "float64"
    },
    {
      "name": "packet_loss",
      "type": "float64"
    },
    {
      "name": "copv_vent",
      "type": "float64"
    },
    {
      "name": "pv1",
      "type": "float64"
    },
    {
      "name": "pv2",
      "type": "float64"
    },
    {
      "name": "vent",
      "type": "float64"
    }
  ]
}